Metadata-Version: 1.1
Name: clihandler
Version: 0.1
Summary: Execute commandline codes directly from python, and iterate through the output.
Home-page: https://github.com/imneonizer/clihandler
Author: Nitin Rai
Author-email: mneonizer@gmail.com
License: MIT
Download-URL: https://github.com/imneonizer/clihandler/archive/v0.1.tar.gz
Keywords: subprocess,Popen,Pipe
Platform: UNKNOWN
Classifier: Development Status :: 4 - Beta
Classifier: Intended Audience :: Developers
Classifier: Topic :: Software Development :: Build Tools
Classifier: License :: OSI Approved :: MIT License
Classifier: Programming Language :: Python :: 3
Classifier: Programming Language :: Python :: 3.4
Classifier: Programming Language :: Python :: 3.5
Classifier: Programming Language :: Python :: 3.6
